django_keycloak_oidc/__init__.py
django_keycloak_oidc/admin.py
django_keycloak_oidc/auth.py
django_keycloak_oidc/context_processor.py
django_keycloak_oidc/forms.py
django_keycloak_oidc/middleware.py
django_keycloak_oidc/models.py
django_keycloak_oidc/urls.py
django_keycloak_oidc/utils.py
django_keycloak_oidc/views.py
django_keycloak_oidc/contrib/__init__.py
django_keycloak_oidc/contrib/drf.py
django_keycloak_oidc/migrations/0001_initial.py
django_keycloak_oidc/migrations/0002_keycloakpermissionmapping_permissions_and_more.py
django_keycloak_oidc/migrations/__init__.py
django_keycloak_oidc/templates/admin/login.html
django_keycloak_oidc-1.0.0.dist-info/licenses/AUTHORS.rst
django_keycloak_oidc-1.0.0.dist-info/licenses/LICENSE
django_keycloak_oidc-1.0.0.dist-info/METADATA
django_keycloak_oidc-1.0.0.dist-info/WHEEL
django_keycloak_oidc-1.0.0.dist-info/top_level.txt
django_keycloak_oidc-1.0.0.dist-info/RECORD
