Metadata-Version: 2.4
Name: django-keycloak-oidc
Version: 1.0.0
Summary: This project is fork of mozilla-django-oidc and modified to map keycloak roles / groups to django user permissions / groups.
Author-email: Mohsen Khodabakhshi <devbynature@proton.me>
License-Expression: MPL-2.0
Project-URL: Homepage, https://github.com/karnameh-tech/django-keycloak-oidc
Project-URL: Documentation, https://github.com/karnameh-tech/django-keycloak-oidc
Keywords: django-keycloak-oidc
Classifier: Development Status :: 5 - Production/Stable
Classifier: Framework :: Django
Classifier: Framework :: Django :: 4.2
Classifier: Framework :: Django :: 5.0
Classifier: Framework :: Django :: 5.1
Classifier: Framework :: Django :: 5.2
Classifier: Intended Audience :: Developers
Classifier: Operating System :: MacOS
Classifier: Operating System :: POSIX :: Linux
Classifier: Natural Language :: English
Classifier: Programming Language :: Python :: 3
Classifier: Programming Language :: Python :: 3 :: Only
Classifier: Programming Language :: Python :: 3.10
Classifier: Programming Language :: Python :: 3.11
Classifier: Programming Language :: Python :: 3.12
Classifier: Programming Language :: Python :: 3.13
Classifier: Programming Language :: Python :: 3.14
Requires-Python: >=3.10
License-File: LICENSE
License-File: AUTHORS.rst
Requires-Dist: Django>=4.2
Requires-Dist: pyjwt
Requires-Dist: requests
Requires-Dist: cryptography
Provides-Extra: drf
Requires-Dist: djangorestframework>=3.14; extra == "drf"
Provides-Extra: test
Requires-Dist: bumpversion; extra == "test"
Requires-Dist: ipython; extra == "test"
Requires-Dist: ipdb; extra == "test"
Requires-Dist: djangorestframework>=3.14; extra == "test"
Requires-Dist: pre-commit; extra == "test"
Requires-Dist: responses; extra == "test"
Requires-Dist: importlib-metadata; python_version < "3.10" and extra == "test"
Requires-Dist: splinter[selenium]>=0.21.0; extra == "test"
Requires-Dist: coverage; extra == "test"
Requires-Dist: tox; extra == "test"
Provides-Extra: lint
Requires-Dist: flake8; extra == "lint"
Provides-Extra: build
Requires-Dist: build; extra == "build"
Provides-Extra: docs
Requires-Dist: sphinx; extra == "docs"
Requires-Dist: sphinx_rtd_theme; extra == "docs"
Provides-Extra: dev
Requires-Dist: django-keycloak-oidc[build,docs,drf,lint,test]; extra == "dev"
Dynamic: license-file
